chatora/dispatch/__init__.py
chatora/dispatch/_pkg_info.py
chatora/dispatch/api.py
chatora/dispatch/dispatch.py
chatora/dispatch/mro_resolver.py
chatora.dispatch-0.1.dist-info/LICENSE.txt
chatora.dispatch-0.1.dist-info/METADATA
chatora.dispatch-0.1.dist-info/WHEEL
chatora.dispatch-0.1.dist-info/top_level.txt
chatora.dispatch-0.1.dist-info/zip-safe
chatora.dispatch-0.1.dist-info/RECORD
