Metadata-Version: 2.1
Name: chatora.dispatch
Version: 0.1
Summary: Multiple argument dispatching for Python.
Home-page: https://github.com/takaomag/chatora.dispatch
Author: Takao Magoori
Author-email: takaomag@users.noreply.github.com
Maintainer: Takao Magoori
Maintainer-email: takaomag@users.noreply.github.com
License: MIT
Download-URL: https://github.com/takaomag/chatora.dispatch/releases
Project-URL: source code, https://github.com/takaomag/chatora.dispatch
Project-URL: issues, https://github.com/takaomag/chatora.dispatch/issues
Project-URL: documentation, https://github.com/takaomag/chatora.dispatch/blob/master/README.md
Keywords: dispatch,overload
Platform: UNKNOWN
Classifier: Development Status :: 4 - Beta
Classifier: Environment :: Other Environment
Classifier: Intended Audience :: Developers
Classifier: License :: OSI Approved :: MIT License
Classifier: Natural Language :: English
Classifier: Operating System :: POSIX :: Linux
Classifier: Programming Language :: Python :: 3 :: Only
Classifier: Programming Language :: Python :: 3.7
Classifier: Programming Language :: Python :: Implementation :: CPython
Classifier: Topic :: Software Development :: Libraries :: Python Modules
Requires-Python: >=3.7
Requires-Dist: setuptools (>=41.0.1)
Requires-Dist: pip (>=19.1.1)
Requires-Dist: wheel (>=0.33.4)
Requires-Dist: packaging (>=19.0)
Provides-Extra: dev
Requires-Dist: bumpversion (>=0.5.3) ; extra == 'dev'
Requires-Dist: check-manifest (>=0.38) ; extra == 'dev'
Requires-Dist: colorama (>=0.4.1) ; extra == 'dev'
Provides-Extra: shell
Requires-Dist: click-completion (>=0.5.1) ; extra == 'shell'
Requires-Dist: click-help-colors (>=0.5) ; extra == 'shell'
